smartpy/__init__.py
smartpy/config.py
smartpy/deprecated/__init__.py
smartpy/internal/__init__.py
smartpy/internal/base.py
smartpy/internal/module_elements.py
smartpy/internal/modules.py
smartpy/internal/sexp.py
smartpy/internal/state.py
smartpy/internal/utils.py
smartpy/libgmp.dylib
smartpy/platform/__init__.py
smartpy/platform/runtime.py
smartpy/platform/services.py
smartpy/public/__init__.py
smartpy/public/exceptions.py
smartpy/public/instantiate_from_metadata.py
smartpy/public/metadata.py
smartpy/public/scenario.py
smartpy/public/scenario_utils.py
smartpy/public/syntax.py
smartpy/public/types.py
smartpy/smartpy-canopy-linux.exe
smartpy/smartpy-canopy-macOS.exe
smartpy/smartpy-docker
smartpy/smartpy-oasis-linux.exe
smartpy/smartpy-oasis-macOS.exe
smartpy/stdlib/__init__.py
smartpy/stdlib/address_utils.spy
smartpy/stdlib/fixed_point.spy
smartpy/stdlib/list_utils.spy
smartpy/stdlib/math.spy
smartpy/stdlib/modules.py
smartpy/stdlib/rational.spy
smartpy/stdlib/statistics.spy
smartpy/stdlib/string_utils.spy
smartpy/stdlib/utils.spy
smartpy/templates/admin_hand_over.py
smartpy/templates/admin_multisig.py
smartpy/templates/atomicSwap.py
smartpy/templates/baking_swap.py
smartpy/templates/bls12_381.py
smartpy/templates/bridge.py
smartpy/templates/calculator.py
smartpy/templates/calculator_main.spy
smartpy/templates/calculator_new.py
smartpy/templates/chain_id.py
smartpy/templates/check_dfs.py
smartpy/templates/chess.py
smartpy/templates/chess_test_3_repeat.py
smartpy/templates/chess_test_checkmate.py
smartpy/templates/chess_test_game1.py
smartpy/templates/chess_test_game2.py
smartpy/templates/collatz.py
smartpy/templates/contract_metadata.py
smartpy/templates/create_contract.py
smartpy/templates/effectful_apply.py
smartpy/templates/escrow.py
smartpy/templates/events.py
smartpy/templates/example_cyclic1.spy
smartpy/templates/example_cyclic2.spy
smartpy/templates/example_cyclic3.spy
smartpy/templates/example_import.spy
smartpy/templates/fa1_2.py
smartpy_tezos-0.23.3.dist-info/LICENSE
smartpy_tezos-0.23.3.dist-info/METADATA
smartpy_tezos-0.23.3.dist-info/WHEEL
smartpy_tezos-0.23.3.dist-info/RECORD
