Metadata-Version: 2.3
Name: smartpy-tezos
Version: 0.23.3
Summary: A comprehensive solution for developing, testing, and deploying smart contracts on the Tezos blockchain.
Author: The SmartPy Team
Requires-Python: >=3.10
Classifier: Programming Language :: Python :: 3
Classifier: Programming Language :: Python :: 3.10
Classifier: Programming Language :: Python :: 3.11
Classifier: Programming Language :: Python :: 3.12
Classifier: Programming Language :: Python :: 3.13
Requires-Dist: requests (>=2.25.1,<3.0.0)
